rocketcontent/README.md
rocketcontent/__init__.py
rocketcontent/admin.md
rocketcontent/base_cache.py
rocketcontent/cache_manager.py
rocketcontent/content_adm_archive_policy.py
rocketcontent/content_adm_config.py
rocketcontent/content_adm_content_class.py
rocketcontent/content_adm_index.py
rocketcontent/content_adm_index_group.py
rocketcontent/content_adm_services_api.py
rocketcontent/content_archive_metadata.py
rocketcontent/content_archive_metadata2.py
rocketcontent/content_archive_policy.py
rocketcontent/content_archive_policy_plus.py
rocketcontent/content_class_navigator.py
rocketcontent/content_config.py
rocketcontent/content_document.py
rocketcontent/content_repository.py
rocketcontent/content_search.py
rocketcontent/content_services_api.py
rocketcontent/content_smart_chat.py
rocketcontent/content_smart_chat_agent.py
rocketcontent/release.md
rocketcontent/test.py
rocketcontent/util.py
rocketcontent/versions_cache.py
rocketcontent-1.2.2.dist-info/METADATA
rocketcontent-1.2.2.dist-info/WHEEL
rocketcontent-1.2.2.dist-info/top_level.txt
rocketcontent-1.2.2.dist-info/RECORD
