Metadata-Version: 2.4
Name: rocketcontent
Version: 1.2.2
Summary: Content Services Api 12.4.x, 12.5.x
Home-page: https://docs.rocketsoftware.com/bundle/mobiusdev_123/page/rtb1690483435152.html
Author: Guillermo Avendano
Author-email: gavendano@rocketsoftware.com
Classifier: Programming Language :: Python :: 3
Classifier: Operating System :: OS Independent
Requires-Python: >=3.9
Requires-Dist: requests
Requires-Dist: PyYAML
Requires-Dist: rich
Requires-Dist: markdown2
Dynamic: author
Dynamic: author-email
Dynamic: classifier
Dynamic: description
Dynamic: description-content-type
Dynamic: home-page
Dynamic: requires-dist
Dynamic: requires-python
Dynamic: summary
